Metadata-Version: 2.4
Name: mock-firestore-sharp
Version: 0.13.17
Summary: In-memory implementation of Google Cloud Firestore for use in tests
Home-page: https://github.com/bziolo-sedric/python-mock-firestore
Author: Matt Dowds
Classifier: Programming Language :: Python :: 3.6
Classifier: Programming Language :: Python :: 3.7
Classifier: Programming Language :: Python :: 3.8
Classifier: Programming Language :: Python :: 3.9
Classifier: Programming Language :: Python :: 3.10
Classifier: License :: OSI Approved :: MIT License
License-File: LICENSE
Dynamic: author
Dynamic: classifier
Dynamic: description
Dynamic: description-content-type
Dynamic: home-page
Dynamic: license-file
Dynamic: summary
